PyNVT-0.0.1.dist-info/DESCRIPTION.rst
PyNVT-0.0.1.dist-info/METADATA
PyNVT-0.0.1.dist-info/RECORD
PyNVT-0.0.1.dist-info/WHEEL
PyNVT-0.0.1.dist-info/metadata.json
PyNVT-0.0.1.dist-info/top_level.txt
pynvt/__init__.py
pynvt/base.py
