Metadata-Version: 2.0
Name: PyNVT
Version: 0.0.1
Summary: Python Neuroimaging Visualization Tools
Home-page: UNKNOWN
Author: SungHo Lee
Author-email: shlee@unc.edu
License: GNLv3
Keywords: Python Neuroimaging Visualization Tools
Platform: UNKNOWN
Classifier: Development Status :: 3 - Alpha
Classifier: Framework :: Jupyter
Classifier: Intended Audience :: Science/Research
Classifier: Topic :: Scientific/Engineering :: Information Analysis
Classifier: Natural Language :: English
Classifier: Programming Language :: Python :: 2.7
